neoepiscope/PSSMHCpan1Sizes.pickle
neoepiscope/__init__.py
neoepiscope/__main__.py
neoepiscope/ambiguousEpitopeID.pickle
neoepiscope/availableAlleles.pickle
neoepiscope/binding_scores.py
neoepiscope/bowtie_index.py
neoepiscope/download.py
neoepiscope/epitopeID.pickle
neoepiscope/file_processing.py
neoepiscope/paths.py
neoepiscope/transcript.py
neoepiscope/transcript_expression.py
neoepiscope/transcript_to_editing.pickle
neoepiscope/transcript_to_editing_hg38.pickle
neoepiscope/version.py
neoepiscope-0.7.0.dist-info/LICENSE
neoepiscope-0.7.0.dist-info/METADATA
neoepiscope-0.7.0.dist-info/WHEEL
neoepiscope-0.7.0.dist-info/entry_points.txt
neoepiscope-0.7.0.dist-info/top_level.txt
neoepiscope-0.7.0.dist-info/zip-safe
neoepiscope-0.7.0.dist-info/RECORD
