Metadata-Version: 2.1
Name: neoepiscope
Version: 0.7.0
Summary: comprehensive neoepitope prediction software
Home-page: http://github.com/ohsu-comp-bio/neoepiscope
Author: Mary A. Wood, Austin Nguyen, Abhinav Nellore, Reid F. Thompson
Author-email: thompsre@ohsu.edu
License: MIT
Download-URL: https://github.com/pdxgx/neoepiscope/tarball/v0.7.0
Keywords: neoepitope,neoantigen,cancer,immunotherapy
Platform: UNKNOWN
Classifier: Programming Language :: Python :: 3
Classifier: License :: OSI Approved :: MIT License
Classifier: Intended Audience :: Science/Research
Classifier: Intended Audience :: Education
Classifier: Operating System :: MacOS
Classifier: Operating System :: Unix
Classifier: Topic :: Scientific/Engineering :: Medical Science Apps.
Classifier: Topic :: Scientific/Engineering :: Bio-Informatics
Requires-Dist: intervaltree (==3.0.2)
Requires-Dist: mhcflurry (>=2.0.0)
Requires-Dist: mhcnuggets
Requires-Dist: networkx
Requires-Dist: pysam (>=0.18.0)
